{
    "0":[
        [
            -19.916435939957765,
            -43.938798701704506
        ]
    ],
    "1":[
        [
            -19.921706737394477,
            -43.94339543841855
        ]
    ],
    "2":[
        [
            -19.92076867797609,
            -43.93472346348565
        ]
    ],
    "3":[
        [
            -19.91502395047781,
            -43.94841301281976
        ]
    ],
    "4":[
        [
            -19.91459742782682,
            -43.95064517761692
        ]
    ],
    "5":[
        [
            -19.9204283759318,
            -43.94479390684679
        ]
    ],
    "6":[
        [
            -19.92661823849592,
            -43.95446085632583
        ]
    ],
    "7":[
        [
            -19.927971076519363,
            -43.94679547411374
        ]
    ],
    "8":[
        [
            -19.92738295511841,
            -43.945924895342536
        ]
    ],
    "9":[
        [
            -19.912920711587994,
            -43.95024145362687
        ]
    ],
    "total_length":13313.07551875208,
    "work_total":1067350.4193725763
}